task1/rom.sv
module rom #(
    parameter ADDRESS_WIDTH = 8,
              DATA_WIDTH = 8
)(
    input logic                        clk,
    input logic [ADDRESS_WIDTH-1:0]    addr,
    output logic [DATA_WIDTH-1:0]      dout
);

    logic [DATA_WIDTH-1:0] rom_array [2**ADDRESS_WIDTH-1:0];

    initial begin
        $display("Loading rom.");
        $readmemh("sinerom.mem", rom_array);
    end

    always_ff @(posedge clk)
        // output is synchronous
        dout <= rom_array[addr];

endmodule

task1/counter.sv
module counter #(
  parameter WIDTH = 8
)(
  // interface signals
  input  logic             clk,      // clock
  input  logic             rst,      // reset
  input logic [WIDTH-1:0] incr,     // increment value
  output logic [WIDTH-1:0] count     // count output
);

always_ff @ (posedge clk)
  if (rst) count <= {WIDTH{1'b0}};
  else     count <= count + {{WIDTH-1{1'b0}}, incr};
endmodule

task1/sinegen.sv
module sinegen #(
    parameter A_WIDTH = 8,
              D_WIDTH = 8
)(
    // interface signals
    input logic                 clk,   // clock
    input logic                 rst,   // reset
    input logic [D_WIDTH-1:0]   incr,  // increment for addr counter
    output logic [D_WIDTH-1:0]  dout   // output data
);

    logic [A_WIDTH-1:0] address;  // interconnect wire

    counter Counter (
        .clk   (clk),
        .rst   (rst),
        .incr  (incr),
        .count (address)
    );

    rom sineRom (
        .clk  (clk),
        .addr (address),
        .dout (dout)
    );

endmodule

task1/sinegen.vcd
$version Generated by VerilatedVcd $end
$date Fri Oct 25 10:48:55 2024 $end
$timescale 1ps $end

 $scope module TOP $end
  $var wire  1 # clk $end
  $var wire  8 & dout [7:0] $end
  $var wire  8 % incr [7:0] $end
  $var wire  1 $ rst $end
  $scope module sinegen $end
   $var wire 32 ( A_WIDTH [31:0] $end
   $var wire 32 ( D_WIDTH [31:0] $end
   $var wire  8 ' address [7:0] $end
   $var wire  1 # clk $end
   $var wire  8 & dout [7:0] $end
   $var wire  8 % incr [7:0] $end
   $var wire  1 $ rst $end
   $scope module Counter $end
    $var wire 32 ( WIDTH [31:0] $end
    $var wire  1 # clk $end
    $var wire  8 ' count [7:0] $end
    $var wire  8 % incr [7:0] $end
    $var wire  1 $ rst $end
   $upscope $end
   $scope module sineRom $end
    $var wire 32 ( ADDRESS_WIDTH [31:0] $end
    $var wire 32 ( DATA_WIDTH [31:0] $end
    $var wire  8 ' addr [7:0] $end
    $var wire  1 # clk $end
    $var wire  8 & dout [7:0] $end
   $upscope $end
  $upscope $end
 $upscope $end
$enddefinitions $end


#0
1#
0$
b00000001 %
b00000000 &
b00000000 '
b00000000000000000000000000001000 (
#1
0#
#2
1#
b00110011 %
b11111110 &
b00000001 '
#3
0#
#4
1#
b11111101 &
b00110100 '
#5
0#
#6
1#
b10100011 &
b01100111 '
#7
0#
#8
1#
b00010111 &
b10011010 '
#9
0#
#10
1#
b00011000 &
b11001101 '
#11
0#
#12
1#
b10100110 &
b00000000 '
#13
0#
#14
1#
b11111110 &
b00110011 '
#15
0#
#16
1#
b10100110 &
b01100110 '
#17
0#
#18
1#
b00011000 &
b10011001 '
#19
0#
#20
1#
b00010111 &
b11001100 '
#21
0#
#22
1#
b10100011 &
b11111111 '
#23
0#
#24
1#
b11111101 &
b00110010 '
#25
0#
#26
1#
b10101001 &
b01100101 '
#27
0#
#28
1#
b00011010 &
b10011000 '
#29
0#
#30
1#
b00010101 &
b11001011 '
#31
0#
#32
1#
b10100000 &
b11111110 '
#33
0#
#34
1#
b11111101 &
b00110001 '
#35
0#
#36
1#
b10101100 &
b01100100 '
#37
0#
#38
1#
b00011100 &
b10010111 '
#39
0#
#40
1#
b00010011 &
b11001010 '
#41
0#
#42
1#
b10011101 &
b11111101 '
#43
0#
#44
1#
b11111101 &
b00110000 '
#45
0#
#46
1#
b10101111 &
b01100011 '
#47
0#
#48
1#
b00011110 &
b10010110 '
#49
0#
#50
1#
b00010010 &
b11001001 '
#51
0#
#52
1#
b10011010 &
b11111100 '
#53
0#
#54
1#
b11111101 &
b00101111 '
#55
0#
#56
1#
b10110010 &
b01100010 '
#57
0#
#58
1#
b00100000 &
b10010101 '
#59
0#
#60
1#
b00010000 &
b11001000 '
#61
0#
#62
1#
b10010111 &
b11111011 '
#63
0#
#64
1#
b11111101 &
b00101110 '
#65
0#
#66
1#
b10110101 &
b01100001 '
#67
0#
#68
1#
b00100011 &
b10010100 '
#69
0#
#70
1#
b00001110 &
b11000111 '
#71
0#
#72
1#
b10010100 &
b11111010 '
#73
0#
#74
1#
b11111100 &
b00101101 '
#75
0#
#76
1#
b10111000 &
b01100000 '
#77
0#
#78
1#
b00100101 &
b10010011 '
#79
0#
#80
1#
b00001101 &
b11000110 '
#81
0#
#82
1#
b10010001 &
b11111001 '
#83
0#
#84
1#
b11111100 &
b00101100 '
#85
0#
#86
1#
b10111010 &
b01011111 '
#87
0#
#88
1#
b00100111 &
b10010010 '
#89
0#
#90
1#
b00001100 &
b11000101 '
#91
0#
#92
1#
b10001110 &
b11111000 '
#93
0#
#94
1#
b11111011 &
b00101011 '
#95
0#
#96
1#
b10111101 &
b01011110 '
#97
0#
#98
1#
b00101001 &
b10010001 '
#99
0#
#100
1#
b00001010 &
b11000100 '
#101
0#
#102
1#
b10001011 &
b11110111 '
#103
0#
#104
1#
b11111010 &
b00101010 '
#105
0#
#106
1#
b11000000 &
b01011101 '
#107
0#
#108
1#
b00101100 &
b10010000 '
#109
0#
#110
1#
b00001001 &
b11000011 '
#111
0#
#112
1#
b10001000 &
b11110110 '
#113
0#
#114
1#
b11111010 &
b00101001 '
#115
0#
#116
1#
b11000010 &
b01011100 '
#117
0#
#118
1#
b00101110 &
b10001111 '
#119
0#
#120
1#
b00001000 &
b11000010 '
#121
0#
#122
1#
b10000101 &
b11110101 '
#123
0#
#124
1#
b11111001 &
b00101000 '
#125
0#
#126
1#
b11000101 &
b01011011 '
#127
0#
#128
1#
b00110000 &
b10001110 '
#129
0#
#130
1#
b00000111 &
b11000001 '
#131
0#
#132
1#
b10000010 &
b11110100 '
#133
0#
#134
1#
b11111000 &
b00100111 '
#135
0#
#136
1#
b11001000 &
b01011010 '
#137
0#
#138
1#
b00110011 &
b10001101 '
#139
0#
#140
1#
b00000110 &
b11000000 '
#141
0#
#142
1#
b01111111 &
b11110011 '
#143
0#
#144
1#
b11110111 &
b00100110 '
#145
0#
#146
1#
b11001010 &
b01011001 '
#147
0#
#148
1#
b00110101 &
b10001100 '
#149
0#
#150
1#
b00000101 &
b10111111 '
#151
0#
#152
1#
b01111011 &
b11110010 '
#153
0#
#154
1#
b11110110 &
b00100101 '
#155
0#
#156
1#
b11001101 &
b01011000 '
#157
0#
#158
1#
b00111000 &
b10001011 '
#159
0#
#160
1#
b00000100 &
b10111110 '
#161
0#
#162
1#
b01111000 &
b11110001 '
#163
0#
#164
1#
b11110101 &
b00100100 '
#165
0#
#166
1#
b11001111 &
b01010111 '
#167
0#
#168
1#
b00111011 &
b10001010 '
#169
0#
#170
1#
b00000011 &
b10111101 '
#171
0#
#172
1#
b01110101 &
b11110000 '
#173
0#
#174
1#
b11110100 &
b00100011 '
#175
0#
#176
1#
b11010001 &
b01010110 '
#177
0#
#178
1#
b00111101 &
b10001001 '
#179
0#
#180
1#
b00000011 &
b10111100 '
#181
0#
#182
1#
b01110010 &
b11101111 '
#183
0#
#184
1#
b11110011 &
b00100010 '
#185
0#
#186
1#
b11010100 &
b01010101 '
#187
0#
#188
1#
b01000000 &
b10001000 '
#189
0#
#190
1#
b00000010 &
b10111011 '
#191
0#
#192
1#
b01101111 &
b11101110 '
#193
0#
#194
1#
b11110001 &
b00100001 '
#195
0#
#196
1#
b11010110 &
b01010100 '
#197
0#
#198
1#
b01000011 &
b10000111 '
#199
0#
#200
1#
b00000001 &
b10111010 '
#201
0#
#202
1#
b01101100 &
b11101101 '
#203
0#
#204
1#
b11110000 &
b00100000 '
#205
0#
#206
1#
b11011000 &
b01010011 '
#207
0#
#208
1#
b01000101 &
b10000110 '
#209
0#
#210
1#
b00000001 &
b10111001 '
#211
0#
#212
1#
b01101001 &
b11101100 '
#213
0#
#214
1#
b11101111 &
b00011111 '
#215
0#
#216
1#
b11011010 &
b01010010 '
#217
0#
#218
1#
b01001000 &
b10000101 '
#219
0#
#220
1#
b00000000 &
b10111000 '
#221
0#
#222
1#
b01100110 &
b11101011 '
#223
0#
#224
1#
b11101101 &
b00011110 '
#225
0#
#226
1#
b11011101 &
b01010001 '
#227
0#
#228
1#
b01001011 &
b10000100 '
#229
0#
#230
1#
b00000000 &
b10110111 '
#231
0#
#232
1#
b01100011 &
b11101010 '
#233
0#
#234
1#
b11101011 &
b00011101 '
#235
0#
#236
1#
b11011111 &
b01010000 '
#237
0#
#238
1#
b01001110 &
b10000011 '
#239
0#
#240
1#
b00000000 &
b10110110 '
#241
0#
#242
1#
b01100000 &
b11101001 '
#243
0#
#244
1#
b11101010 &
b00011100 '
#245
0#
#246
1#
b11100001 &
b01001111 '
#247
0#
#248
1#
b01010001 &
b10000010 '
#249
0#
#250
1#
b00000000 &
b10110101 '
#251
0#
#252
1#
b01011101 &
b11101000 '
#253
0#
#254
1#
b11101000 &
b00011011 '
#255
0#
#256
1#
b11100011 &
b01001110 '
#257
0#
#258
1#
b01010100 &
b10000001 '
#259
0#
#260
1#
b00000000 &
b10110100 '
#261
0#
#262
1#
b01011010 &
b11100111 '
#263
0#
#264
1#
b11100110 &
b00011010 '
#265
0#
#266
1#
b11100101 &
b01001101 '
#267
0#
#268
1#
b01010111 &
b10000000 '
#269
0#
#270
1#
b00000000 &
b10110011 '
#271
0#
#272
1#
b01010111 &
b11100110 '
#273
0#
#274
1#
b11100101 &
b00011001 '
#275
0#
#276
1#
b11100110 &
b01001100 '
#277
0#
#278
1#
b01011010 &
b01111111 '
#279
0#
#280
1#
b00000000 &
b10110010 '
#281
0#
#282
1#
b01010100 &
b11100101 '
#283
0#
#284
1#
b11100011 &
b00011000 '
#285
0#
#286
1#
b11101000 &
b01001011 '
#287
0#
#288
1#
b01011101 &
b01111110 '
#289
0#
#290
1#
b00000000 &
b10110001 '
#291
0#
#292
1#
b01010001 &
b11100100 '
#293
0#
#294
1#
b11100001 &
b00010111 '
#295
0#
#296
1#
b11101010 &
b01001010 '
#297
0#
#298
1#
b01100000 &
b01111101 '
#299
0#
#300
1#
b00000000 &
b10110000 '
#301
0#
#302
1#
b01001110 &
b11100011 '
#303
0#
#304
1#
b00110010 %
b11011111 &
b00010110 '
#305
0#
#306
1#
b11101011 &
b01001000 '
#307
0#
#308
1#
b01100110 &
b01111010 '
#309
0#
#310
1#
b00110001 %
b00000001 &
b10101100 '
#311
0#
#312
1#
b00110000 %
b01000011 &
b11011101 '
#313
0#
#314
1#
b11010001 &
b00001101 '
#315
0#
#316
1#
b11110111 &
b00111101 '
#317
0#
#318
1#
b00101111 %
b10001000 &
b01101101 '
#319
0#
#320
1#
b00001101 &
b10011100 '
#321
0#
#322
1#
b00101110 %
b00011100 &
b11001011 '
#323
0#
#324
1#
b00101101 %
b10100000 &
b11111001 '
#325
0#
#326
1#
b00101100 %
b11111100 &
b00100110 '
#327
0#
#328
1#
b00101011 %
b11001010 &
b01010010 '
#329
0#
#330
1#
b01001000 &
b01111101 '
#331
0#
#332
1#
b00000000 &
b10101000 '
#333
0#
#334
1#
b00111000 &
b11010011 '
#335
0#
#336
1#
b10111000 &
b11111110 '
#337
0#
#338
1#
b11111101 &
b00101001 '
#339
0#
#340
1#
b11000010 &
b01010100 '
#341
0#
#342
1#
b01000011 &
b01111111 '
#343
0#
#344
1#
b00000000 &
b10101010 '
#345
0#
#346
1#
b00111101 &
b11010101 '
#347
0#
#348
1#
b10111101 &
b00000000 '
#349
0#
#350
1#
b11111110 &
b00101011 '
#351
0#
#352
1#
b10111101 &
b01010110 '
#353
0#
#354
1#
b00111101 &
b10000001 '
#355
0#
#356
1#
b00000000 &
b10101100 '
#357
0#
#358
1#
b00101010 %
b01000011 &
b11010111 '
#359
0#
#360
1#
b11000010 &
b00000001 '
#361
0#
#362
1#
b11111101 &
b00101011 '
#363
0#
#364
1#
b00101001 %
b10111101 &
b01010101 '
#365
0#
#366
1#
b01000000 &
b01111110 '
#367
0#
#368
1#
b00100111 %
b00000000 &
b10100111 '
#369
0#
#370
1#
b00100101 %
b00110101 &
b11001110 '
#371
0#
#372
1#
b00100100 %
b10101001 &
b11110011 '
#373
0#
#374
1#
b11110111 &
b00010111 '
#375
0#
#376
1#
b00100011 %
b11101010 &
b00111011 '
#377
0#
#378
1#
b10001110 &
b01011110 '
#379
0#
#380
1#
b00100001 %
b00101001 &
b10000001 '
#381
0#
#382
1#
b00100000 %
b00000000 &
b10100010 '
#383
0#
#384
1#
b00011111 %
b00101001 &
b11000010 '
#385
0#
#386
1#
b10000101 &
b11100001 '
#387
0#
#388
1#
b11011010 &
b00000000 '
#389
0#
#390
1#
b11111110 &
b00011111 '
#391
0#
#392
1#
b11011010 &
b00111110 '
#393
0#
#394
1#
b10000101 &
b01011101 '
#395
0#
#396
1#
b00101100 &
b01111100 '
#397
0#
#398
1#
b00000000 &
b10011011 '
#399
0#
#400
1#
b00011010 &
b10111010 '
#401
0#
#402
1#
b01101100 &
b11011001 '
#403
0#
#404
1#
b11001000 &
b11111000 '
#405
0#
#406
1#
b11111011 &
b00010111 '
#407
0#
#408
1#
b11101010 &
b00110110 '
#409
0#
#410
1#
b10011101 &
b01010101 '
#411
0#
#412
1#
b01000000 &
b01110100 '
#413
0#
#414
1#
b00000101 &
b10010011 '
#415
0#
#416
1#
b00001101 &
b10110010 '
#417
0#
#418
1#
b01010100 &
b11010001 '
#419
0#
#420
1#
b10110010 &
b11110000 '
#421
0#
#422
1#
b11110100 &
b00001111 '
#423
0#
#424
1#
b00011110 %
b11110101 &
b00101110 '
#425
0#
#426
1#
b10110101 &
b01001100 '
#427
0#
#428
1#
b00011101 %
b01011010 &
b01101010 '
#429
0#
#430
1#
b00011011 %
b00010010 &
b10000111 '
#431
0#
#432
1#
b00000001 &
b10100010 '
#433
0#
#434
1#
b00011010 %
b00101001 &
b10111101 '
#435
0#
#436
1#
b00011001 %
b01110101 &
b11010111 '
#437
0#
#438
1#
b00010111 %
b11000010 &
b11110000 '
#439
0#
#440
1#
b00010110 %
b11110100 &
b00000111 '
#441
0#
#442
1#
b00010100 %
b11111100 &
b00011101 '
#443
0#
#444
1#
b00010011 %
b11011111 &
b00110001 '
#445
0#
#446
1#
b00010010 %
b10101100 &
b01000100 '
#447
0#
#448
1#
b01110010 &
b01010110 '
#449
0#
#450
1#
b00111101 &
b01101000 '
#451
0#
#452
1#
b00010101 &
b01111010 '
#453
0#
#454
1#
b00000001 &
b10001100 '
#455
0#
#456
1#
b00000101 &
b10011110 '
#457
0#
#458
1#
b00100000 &
b10110000 '
#459
0#
#460
1#
b01001110 &
b11000010 '
#461
0#
#462
1#
b10000101 &
b11010100 '
#463
0#
#464
1#
b10111010 &
b11100110 '
#465
0#
#466
1#
b11100101 &
b11111000 '
#467
0#
#468
1#
b11111011 &
b00001010 '
#469
0#
#470
1#
b11111010 &
b00011100 '
#471
0#
#472
1#
b11100001 &
b00101110 '
#473
0#
#474
1#
b10110101 &
b01000000 '
#475
0#
#476
1#
b01111110 &
b01010010 '
#477
0#
#478
1#
b01001000 &
b01100100 '
#479
0#
#480
1#
b00011100 &
b01110110 '
#481
0#
#482
1#
b00000011 &
b10001000 '
#483
0#
#484
1#
b00000010 &
b10011010 '
#485
0#
#486
1#
b00011000 &
b10101100 '
#487
0#
#488
1#
b01000011 &
b10111110 '
#489
0#
#490
1#
b01111000 &
b11010000 '
#491
0#
#492
1#
b10101111 &
b11100010 '
#493
0#
#494
1#
b00010001 %
b11011101 &
b11110100 '
#495
0#
#496
1#
b11111000 &
b00000101 '
#497
0#
#498
1#
b00010000 %
b11111101 &
b00010110 '
#499
0#
#500
1#
b00001111 %
b11101011 &
b00100110 '
#501
0#
#502
1#
b00001110 %
b11001010 &
b00110101 '
#503
0#
#504
1#
b00001101 %
b10100000 &
b01000011 '
#505
0#
#506
1#
b00001100 %
b01110101 &
b01010000 '
#507
0#
#508
1#
b01001110 &
b01011100 '
#509
0#
#510
1#
b00001010 %
b00101110 &
b01101000 '
#511
0#
#512
1#
b00001001 %
b00010101 &
b01110010 '
#513
0#
#514
1#
b00000111 &
b01111011 '
#515
0#
#516
1#
b00000000 &
b10000100 '
#517
0#
#518
1#
b10001101 '
#519
0#
#520
1#
b00000110 &
b10010110 '
#521
0#
#522
1#
b00010010 &
b10011111 '
#523
0#
#524
1#
b00100011 &
b10101000 '
#525
0#
#526
1#
b00111000 &
b10110001 '
#527
0#
#528
1#
b01010001 &
b10111010 '
#529
0#
#530
1#
b01101100 &
b11000011 '
#531
0#
#532
1#
b10001000 &
b11001100 '
#533
0#
#534
1#
b10100011 &
b11010101 '
#535
0#
#536
1#
b10111101 &
b11011110 '
#537
0#
#538
1#
b11010100 &
b11100111 '
#539
0#
#540
1#
b11100110 &
b11110000 '
#541
0#
#542
1#
b11110100 &
b11111001 '
#543
0#
#544
1#
b11111100 &
b00000010 '
#545
0#
#546
1#
b11111101 &
b00001011 '
#547
0#
#548
1#
b11111001 &
b00010100 '
#549
0#
#550
1#
b00001000 %
b11101111 &
b00011101 '
#551
0#
#552
1#
b00000111 %
b11011111 &
b00100101 '
#553
0#
#554
1#
b11001101 &
b00101100 '
#555
0#
#556
1#
b10111010 &
b00110011 '
#557
0#
#558
1#
b10100110 &
b00111010 '
#559
0#
#560
1#
b00000110 %
b10010001 &
b01000001 '
#561
0#
#562
1#
b01111011 &
b01000111 '
#563
0#
#564
1#
b01101001 &
b01001101 '
#565
0#
#566
1#
b01010111 &
b01010011 '
#567
0#
#568
1#
b01000101 &
b01011001 '
#569
0#
#570
1#
b00110101 &
b01011111 '
#571
0#
#572
1#
b00100111 &
b01100101 '
#573
0#
#574
1#
b00011010 &
b01101011 '
#575
0#
#576
1#
b00010000 &
b01110001 '
#577
0#
#578
1#
b00000101 %
b00001000 &
b01110111 '
#579
0#
#580
1#
b00000011 &
b01111100 '
#581
0#
#582
1#
b00000000 &
b10000001 '
#583
0#
#584
1#
b00000100 %
b10000110 '
#585
0#
#586
1#
b00000001 &
b10001010 '
#587
0#
#588
1#
b00000011 &
b10001110 '
#589
0#
#590
1#
b00000111 &
b10010010 '
#591
0#
#592
1#
b00001100 &
b10010110 '
#593
0#
#594
1#
b00010010 &
b10011010 '
#595
0#
#596
1#
b00000011 %
b00011000 &
b10011110 '
#597
0#
#598
1#
b00100000 &
b10100001 '
#599
0#
#600
1#
b00100111 &
b10100100 '
#601
0#
#602
1#
b00101110 &
b10100111 '
#603
0#
#604
1#
b00110101 &
b10101010 '
#605
0#
#606
1#
b00111101 &
b10101101 '
#607
0#
#608
1#
b01000101 &
b10110000 '
#609
0#
#610
1#
b00000010 %
b01001110 &
b10110011 '
#611
0#
#612
1#
b01010111 &
b10110101 '
#613
0#
#614
1#
b01011101 &
b10110111 '
#615
0#
#616
1#
b01100011 &
b10111001 '
#617
0#
#618
1#
b01101001 &
b10111011 '
#619
0#
#620
1#
b01101111 &
b10111101 '
#621
0#
#622
1#
b00000001 %
b01110101 &
b10111111 '
#623
0#
#624
1#
b01111011 &
b11000000 '
#625
0#
#626
1#
b01111111 &
b11000001 '
#627
0#
#628
1#
b10000010 &
b11000010 '
#629
0#
#630
1#
b10000101 &
b11000011 '
#631
0#
#632
1#
b10001000 &
b11000100 '
#633
0#
#634
1#
b10001011 &
b11000101 '
#635
0#
#636
1#
b10001110 &
b11000110 '
#637
0#
#638
1#
b10010001 &
b11000111 '
#639
0#
#640
1#
b10010100 &
b11001000 '
#641
0#
#642
1#
b10010111 &
b11001001 '
#643
0#
#644
1#
b10011010 &
b11001010 '
#645
0#
#646
1#
b10011101 &
b11001011 '
#647
0#
#648
1#
b10100000 &
b11001100 '
#649
0#
#650
1#
b10100011 &
b11001101 '
#651
0#
#652
1#
b10100110 &
b11001110 '
#653
0#
#654
1#
b10101001 &
b11001111 '
#655
0#
#656
1#
b10101100 &
b11010000 '
#657
0#
#658
1#
b10101111 &
b11010001 '
#659
0#
#660
1#
b10110010 &
b11010010 '
#661
0#
#662
1#
b10110101 &
b11010011 '
#663
0#
#664
1#
b10111000 &
b11010100 '
#665
0#
#666
1#
b10111010 &
b11010101 '
#667
0#
#668
1#
b10111101 &
b11010110 '
#669
0#
#670
1#
b11000000 &
b11010111 '
#671
0#
#672
1#
b11000010 &
b11011000 '
#673
0#
#674
1#
b11000101 &
b11011001 '
#675
0#
#676
1#
b11001000 &
b11011010 '
#677
0#
#678
1#
b11001010 &
b11011011 '
#679
0#
#680
1#
b11001101 &
b11011100 '
#681
0#
#682
1#
b11001111 &
b11011101 '
#683
0#
#684
1#
b11010001 &
b11011110 '
#685
0#
#686
1#
b11010100 &
b11011111 '
#687
0#
#688
1#
b11010110 &
b11100000 '
#689
0#
#690
1#
b11011000 &
b11100001 '
#691
0#
#692
1#
b11011010 &
b11100010 '
#693
0#
#694
1#
b11011101 &
b11100011 '
#695
0#
#696
1#
b11011111 &
b11100100 '
#697
0#
#698
1#
b11100001 &
b11100101 '
#699
0#
#700
1#
b11100011 &
b11100110 '
#701
0#
#702
1#
b11100101 &
b11100111 '
#703
0#
#704
1#
b11100110 &
b11101000 '
#705
0#
#706
1#
b11101000 &
b11101001 '
#707
0#
#708
1#
b11101010 &
b11101010 '
#709
0#
#710
1#
b11101011 &
b11101011 '
#711
0#
#712
1#
b11101101 &
b11101100 '
#713
0#
#714
1#
b11101111 &
b11101101 '
#715
0#
#716
1#
b11110000 &
b11101110 '
#717
0#
#718
1#
b11110001 &
b11101111 '
#719
0#
#720
1#
b11110011 &
b11110000 '
#721
0#
#722
1#
b11110100 &
b11110001 '
#723
0#
#724
1#
b11110101 &
b11110010 '
#725
0#
#726
1#
b11110110 &
b11110011 '
#727
0#
#728
1#
b11110111 &
b11110100 '
#729
0#
#730
1#
b11111000 &
b11110101 '
#731
0#
#732
1#
b11111001 &
b11110110 '
#733
0#
#734
1#
b11111010 &
b11110111 '
#735
0#
#736
1#
b11111000 '
#737
0#
#738
1#
b11111011 &
b11111001 '
#739
0#
#740
1#
b11111100 &
b11111010 '
#741
0#
#742
1#
b11111011 '
#743
0#
#744
1#
b11111101 &
b11111100 '
#745
0#
#746
1#
b11111101 '
#747
0#
#748
1#
b11111110 '
#749
0#
#750
1#
b11111111 '
#751
0#
#752
1#
b00000000 '
#753
0#
#754
1#
b11111110 &
b00000001 '
#755
0#
#756
1#
b11111101 &
b00000010 '
#757
0#
#758
1#
b00000011 '
#759
0#
#760
1#
b00000100 '
#761
0#
#762
1#
b00000101 '
#763
0#
#764
1#
b00000110 '
#765
0#
#766
1#
b11111100 &
b00000111 '
#767
0#
#768
1#
b00001000 '
#769
0#
#770
1#
b11111011 &
b00001001 '
#771
0#
#772
1#
b11111010 &
b00001010 '
#773
0#
#774
1#
b00001011 '
#775
0#
#776
1#
b11111001 &
b00001100 '
#777
0#
#778
1#
b11111000 &
b00001101 '
#779
0#
#780
1#
b11110111 &
b00001110 '
#781
0#
#782
1#
b11110110 &
b00001111 '
#783
0#
#784
1#
b11110101 &
b00010000 '
#785
0#
#786
1#
b11110100 &
b00010001 '
#787
0#
#788
1#
b11110011 &
b00010010 '
#789
0#
#790
1#
b11110001 &
b00010011 '
#791
0#
#792
1#
b11110000 &
b00010100 '
#793
0#
#794
1#
b11101111 &
b00010101 '
#795
0#
#796
1#
b11101101 &
b00010110 '
#797
0#
#798
1#
b11101011 &
b00010111 '
#799
0#
#800
1#
b11101010 &
b00011000 '
#801
0#
#802
1#
b11101000 &
b00011001 '
#803
0#
#804
1#
b11100110 &
b00011010 '
#805
0#
#806
1#
b11100101 &
b00011011 '
#807
0#
#808
1#
b11100011 &
b00011100 '
#809
0#
#810
1#
b11100001 &
b00011101 '
#811
0#
#812
1#
b11011111 &
b00011110 '
#813
0#
#814
1#
b11011101 &
b00011111 '
#815
0#
#816
1#
b11011010 &
b00100000 '
#817
0#
#818
1#
b11011000 &
b00100001 '
#819
0#
#820
1#
b11010110 &
b00100010 '
#821
0#
#822
1#
b11010100 &
b00100011 '
#823
0#
#824
1#
b11010001 &
b00100100 '
#825
0#
#826
1#
b11001111 &
b00100101 '
#827
0#
#828
1#
b11001101 &
b00100110 '
#829
0#
#830
1#
b11001010 &
b00100111 '
#831
0#
#832
1#
b11001000 &
b00101000 '
#833
0#
#834
1#
b11000101 &
b00101001 '
#835
0#
#836
1#
b11000010 &
b00101010 '
#837
0#
#838
1#
b11000000 &
b00101011 '
#839
0#
#840
1#
b10111101 &
b00101100 '
#841
0#
#842
1#
b10111010 &
b00101101 '
#843
0#
#844
1#
b10111000 &
b00101110 '
#845
0#
#846
1#
b10110101 &
b00101111 '
#847
0#
#848
1#
b10110010 &
b00110000 '
#849
0#
#850
1#
b10101111 &
b00110001 '
#851
0#
#852
1#
b10101100 &
b00110010 '
#853
0#
#854
1#
b10101001 &
b00110011 '
#855
0#
#856
1#
b10100110 &
b00110100 '
#857
0#
#858
1#
b10100011 &
b00110101 '
#859
0#
#860
1#
b10100000 &
b00110110 '
#861
0#
#862
1#
b10011101 &
b00110111 '
#863
0#
#864
1#
b10011010 &
b00111000 '
#865
0#
#866
1#
b10010111 &
b00111001 '
#867
0#
#868
1#
b10010100 &
b00111010 '
#869
0#
#870
1#
b10010001 &
b00111011 '
#871
0#
#872
1#
b10001110 &
b00111100 '
#873
0#
#874
1#
b10001011 &
b00111101 '
#875
0#
#876
1#
b10001000 &
b00111110 '
#877
0#
#878
1#
b10000101 &
b00111111 '
#879
0#
#880
1#
b10000010 &
b01000000 '
#881
0#
#882
1#
b01111110 &
b01000001 '
#883
0#
#884
1#
b01111011 &
b01000010 '
#885
0#
#886
1#
b01111000 &
b01000011 '
#887
0#
#888
1#
b01110101 &
b01000100 '
#889
0#
#890
1#
b01110010 &
b01000101 '
#891
0#
#892
1#
b01101111 &
b01000110 '
#893
0#
#894
1#
b01101100 &
b01000111 '
#895
0#
#896
1#
b01101001 &
b01001000 '
#897
0#
#898
1#
b01100110 &
b01001001 '
#899
0#
#900
1#
b01100011 &
b01001010 '
#901
0#
#902
1#
b01100000 &
b01001011 '
#903
0#
#904
1#
b01011101 &
b01001100 '
#905
0#
#906
1#
b01011010 &
b01001101 '
#907
0#
#908
1#
b01010111 &
b01001110 '
#909
0#
#910
1#
b01010100 &
b01001111 '
#911
0#
#912
1#
b01010001 &
b01010000 '
#913
0#
#914
1#
b01001110 &
b01010001 '
#915
0#
#916
1#
b01001011 &
b01010010 '
#917
0#
#918
1#
b01001000 &
b01010011 '
#919
0#
#920
1#
b01000101 &
b01010100 '
#921
0#
#922
1#
b01000011 &
b01010101 '
#923
0#
#924
1#
b01000000 &
b01010110 '
#925
0#
#926
1#
b00111101 &
b01010111 '
#927
0#
#928
1#
b00111011 &
b01011000 '
#929
0#
#930
1#
b00111000 &
b01011001 '
#931
0#
#932
1#
b00110101 &
b01011010 '
#933
0#
#934
1#
b00110011 &
b01011011 '
#935
0#
#936
1#
b00110000 &
b01011100 '
#937
0#
#938
1#
b00101110 &
b01011101 '
#939
0#
#940
1#
b00101100 &
b01011110 '
#941
0#
#942
1#
b00101001 &
b01011111 '
#943
0#
#944
1#
b00100111 &
b01100000 '
#945
0#
#946
1#
b00100101 &
b01100001 '
#947
0#
#948
1#
b00100011 &
b01100010 '
#949
0#
#950
1#
b00100000 &
b01100011 '
#951
0#
#952
1#
b00011110 &
b01100100 '
#953
0#
#954
1#
b00011100 &
b01100101 '
#955
0#
#956
1#
b00011010 &
b01100110 '
#957
0#
#958
1#
b00011000 &
b01100111 '
#959
0#
#960
1#
b00010111 &
b01101000 '
#961
0#
#962
1#
b00010101 &
b01101001 '
#963
0#
#964
1#
b00010011 &
b01101010 '
#965
0#
#966
1#
b00010010 &
b01101011 '
#967
0#
#968
1#
b00010000 &
b01101100 '
#969
0#
#970
1#
b00001110 &
b01101101 '
#971
0#
#972
1#
b00001101 &
b01101110 '
#973
0#
#974
1#
b00001100 &
b01101111 '
#975
0#
#976
1#
b00001010 &
b01110000 '
#977
0#
#978
1#
b00001001 &
b01110001 '
#979
0#
#980
1#
b00001000 &
b01110010 '
#981
0#
#982
1#
b00000111 &
b01110011 '
#983
0#
#984
1#
b00000110 &
b01110100 '
#985
0#
#986
1#
b00000101 &
b01110101 '
#987
0#
#988
1#
b00000100 &
b01110110 '
#989
0#
#990
1#
b00000011 &
b01110111 '
#991
0#
#992
1#
b01111000 '
#993
0#
#994
1#
b00000010 &
b01111001 '
#995
0#
#996
1#
b00000001 &
b01111010 '
#997
0#
#998
1#
b01111011 '
#999
0#
#1000
1#
b00000000 &
b01111100 '
#1001
0#
#1002
1#
b01111101 '
#1003
0#
#1004
1#
b01111110 '
#1005
0#
#1006
1#
b01111111 '
#1007
0#
#1008
1#
b10000000 '
#1009
0#
#1010
1#
b10000001 '
#1011
0#
#1012
1#
b10000010 '
#1013
0#
#1014
1#
b10000011 '
#1015
0#
#1016
1#
b10000100 '
#1017
0#
#1018
1#
b10000101 '
#1019
0#
#1020
1#
b10000110 '
#1021
0#
#1022
1#
b00000001 &
b10000111 '
#1023
0#
#1024
1#
b10001000 '
#1025
0#
#1026
1#
b00000010 &
b10001001 '
#1027
0#
#1028
1#
b00000011 &
b10001010 '
#1029
0#
#1030
1#
b10001011 '
#1031
0#
#1032
1#
b00000100 &
b10001100 '
#1033
0#
#1034
1#
b00000101 &
b10001101 '
#1035
0#
#1036
1#
b00000110 &
b10001110 '
#1037
0#
#1038
1#
b00000111 &
b10001111 '
#1039
0#
#1040
1#
b00001000 &
b10010000 '
#1041
0#
#1042
1#
b00001001 &
b10010001 '
#1043
0#
